mcp_codegen/__init__.py
mcp_codegen/cli.py
mcp_codegen/mcp_proj_codegen.py
mcp_codegen/_yaml/__init__.py
mcp_codegen/yaml/__init__.py
mcp_codegen/yaml/composer.py
mcp_codegen/yaml/constructor.py
mcp_codegen/yaml/cyaml.py
mcp_codegen/yaml/dumper.py
mcp_codegen/yaml/emitter.py
mcp_codegen/yaml/error.py
mcp_codegen/yaml/events.py
mcp_codegen/yaml/loader.py
mcp_codegen/yaml/nodes.py
mcp_codegen/yaml/parser.py
mcp_codegen/yaml/reader.py
mcp_codegen/yaml/representer.py
mcp_codegen/yaml/resolver.py
mcp_codegen/yaml/scanner.py
mcp_codegen/yaml/serializer.py
mcp_codegen/yaml/tokens.py
mcp_codegen-1.0.3.dist-info/licenses/LICENSE.txt
mcp_codegen-1.0.3.dist-info/METADATA
mcp_codegen-1.0.3.dist-info/WHEEL
mcp_codegen-1.0.3.dist-info/entry_points.txt
mcp_codegen-1.0.3.dist-info/top_level.txt
mcp_codegen-1.0.3.dist-info/RECORD
