Metadata-Version: 2.4
Name: mcp_codegen
Version: 1.0.3
Summary: Python Package to provide assistance in generating MCP server project.
Author-email: Biprajeet Kar <biprokvs@gmail.com>
Maintainer-email: Biprajeet Kar <biprokvs@gmail.com>
License-Expression: MIT
Classifier: Programming Language :: Python :: 3
Classifier: Operating System :: OS Independent
Requires-Python: >=3.9
License-File: LICENSE.txt
Requires-Dist: click
Dynamic: license-file
